MANIFEST.in
README.txt
bootstrap.py
buildout.cfg
setup.cfg
setup.py
blockdiagcontrib/__init__.py
blockdiagcontrib/nationalflags.py
blockdiagcontrib/images/nationalflags/106px-Flag_of_Switzerland.svg.png
blockdiagcontrib/images/nationalflags/106px-Flag_of_the_Vatican_City.svg.png
blockdiagcontrib/images/nationalflags/114px-Flag_of_Belgium.svg.png
blockdiagcontrib/images/nationalflags/115px-Flag_of_Niger.svg.png
blockdiagcontrib/images/nationalflags/119px-Flag_of_Monaco.svg.png
blockdiagcontrib/images/nationalflags/122px-Flag_of_Denmark.svg.png
blockdiagcontrib/images/nationalflags/122px-Flag_of_Gabon.svg.png
blockdiagcontrib/images/nationalflags/122px-Flag_of_Papua_New_Guinea.svg.png
blockdiagcontrib/images/nationalflags/122px-Flag_of_San_Marino.svg.png
blockdiagcontrib/images/nationalflags/124px-Flag_of_Israel.svg.png
blockdiagcontrib/images/nationalflags/124px-Flag_of_Norway.svg.png
blockdiagcontrib/images/nationalflags/125px-Flag_of_Albania.svg.png
blockdiagcontrib/images/nationalflags/125px-Flag_of_Iceland.svg.png
blockdiagcontrib/images/nationalflags/127px-Flag_of_Andorra.svg.png
blockdiagcontrib/images/nationalflags/127px-Flag_of_Brazil.svg.png
blockdiagcontrib/images/nationalflags/130px-Flag_of_Afghanistan.svg.png
blockdiagcontrib/images/nationalflags/130px-Flag_of_Algeria.svg.png
blockdiagcontrib/images/nationalflags/130px-Flag_of_Angola.svg.png
blockdiagcontrib/images/nationalflags/130px-Flag_of_Antigua_and_Barbuda.svg.png
blockdiagcontrib/images/nationalflags/130px-Flag_of_Austria.svg.png
blockdiagcontrib/images/nationalflags/130px-Flag_of_Barbados.svg.png
blockdiagcontrib/images/nationalflags/130px-Flag_of_Belize.svg.png
blockdiagcontrib/images/nationalflags/130px-Flag_of_Benin.svg.png
blockdiagcontrib/images/nationalflags/130px-Flag_of_Bhutan.svg.png
blockdiagcontrib/images/nationalflags/130px-Flag_of_Bolivia.svg.png
blockdiagcontrib/images/nationalflags/130px-Flag_of_Botswana.svg.png
blockdiagcontrib/images/nationalflags/130px-Flag_of_Bulgaria.svg.png
blockdiagcontrib_nationalflags.egg-info/PKG-INFO
blockdiagcontrib_nationalflags.egg-info/SOURCES.txt
blockdiagcontrib_nationalflags.egg-info/dependency_links.txt
blockdiagcontrib_nationalflags.egg-info/entry_points.txt
blockdiagcontrib_nationalflags.egg-info/namespace_packages.txt
blockdiagcontrib_nationalflags.egg-info/requires.txt
blockdiagcontrib_nationalflags.egg-info/top_level.txt